
[
  {
    "idPersona": 1,
    "perIdentificacion": "11",
    "perNombres": "Pedro",
    "perApellidos": "Ruiz",
    "perGenero": "masculino",
    "perCorreo": "pruiz@gmail.com                                   ",
    "perFechaNacimiento": "1991-12-20T00:00:00"
  },
  {
    "idPersona": 3,
    "perIdentificacion": "10",
    "perNombres": "Axel",
    "perApellidos": "Huaman",
    "perGenero": "masculino",
    "perCorreo": "axell@hotmail.com                                 ",
    "perFechaNacimiento": "1999-09-25T00:00:00"
  },
  {
    "idPersona": 4,
    "perIdentificacion": "4",
    "perNombres": "Maria",
    "perApellidos": "Monzon",
    "perGenero": "femenino",
    "perCorreo": "Mmomnzon@hotmail.com                              ",
    "perFechaNacimiento": "1996-07-12T00:00:00"
  },
  {
    "idPersona": 6,
    "perIdentificacion": "2",
    "perNombres": "Luis",
    "perApellidos": "Mendoza",
    "perGenero": "masculino",
    "perCorreo": "Luis56@gmail.com                                  ",
    "perFechaNacimiento": "1990-06-23T00:00:00"
  },
  {
    "idPersona": 7,
    "perIdentificacion": "12",
    "perNombres": "Claudia",
    "perApellidos": "Arellano",
    "perGenero": "femenino",
    "perCorreo": "Claudiaare@gmail.com                              ",
    "perFechaNacimiento": "2000-05-26T00:00:00"
  },
  {
    "idPersona": 8,
    "perIdentificacion": "13",
    "perNombres": "Fernanda",
    "perApellidos": "Rojas",
    "perGenero": "femenino",
    "perCorreo": "765rojas@hotmail.com                              ",
    "perFechaNacimiento": "1999-12-26T00:00:00"
  },
  {
    "idPersona": 9,
    "perIdentificacion": "14",
    "perNombres": "Astrid",
    "perApellidos": "Ocaña",
    "perGenero": "femenino",
    "perCorreo": "ocaña@hotmail.com                                 ",
    "perFechaNacimiento": "1992-05-30T00:00:00"
  },
  {
    "idPersona": 10,
    "perIdentificacion": "15",
    "perNombres": "Alvaro",
    "perApellidos": "Sarmiento",
    "perGenero": "masculino",
    "perCorreo": "sarmiento26@gmail.com                             ",
    "perFechaNacimiento": "1999-11-26T00:00:00"
  },
  {
    "idPersona": 11,
    "perIdentificacion": "16",
    "perNombres": "Cristian",
    "perApellidos": "Faustino",
    "perGenero": "masculino",
    "perCorreo": "elrey@hotmail.com                                 ",
    "perFechaNacimiento": "1999-06-16T00:00:00"
  },
  {
    "idPersona": 12,
    "perIdentificacion": "17",
    "perNombres": "Ana",
    "perApellidos": "Navarro",
    "perGenero": "femenino",
    "perCorreo": "anamaria@hotmail.com                              ",
    "perFechaNacimiento": "1948-01-13T00:00:00"
  },
  {
    "idPersona": 13,
    "perIdentificacion": "18",
    "perNombres": "Oscar",
    "perApellidos": "Huaman",
    "perGenero": "masculino",
    "perCorreo": "isminio@gmail.com                                 ",
    "perFechaNacimiento": "1963-02-16T00:00:00"
  },
  {
    "idPersona": 14,
    "perIdentificacion": "19",
    "perNombres": "Agustina",
    "perApellidos": "Rojas",
    "perGenero": "femenino",
    "perCorreo": "tugatita@gmail.com                                ",
    "perFechaNacimiento": "1962-08-12T00:00:00"
  },
  {
    "idPersona": 16,
    "perIdentificacion": "20",
    "perNombres": "Brando ",
    "perApellidos": "Mendoza",
    "perGenero": "masculino",
    "perCorreo": "mendozaL@hotmail.com                              ",
    "perFechaNacimiento": "2000-06-14T00:00:00"
  }
]